{"client":"rho.cs.oswego.edu","server":"pi.cs.oswego.edu","type":"UDP","rtt":[{"message_size":1,"total_time":0.082227},{"message_size":1,"total_time":0.113702},{"message_size":1,"total_time":0.100462},{"message_size":1,"total_time":0.101808},{"message_size":1,"total_time":0.109268},{"message_size":64,"total_time":0.108914},{"message_size":64,"total_time":0.11606},{"message_size":64,"total_time":0.105313},{"message_size":64,"total_time":0.101033},{"message_size":64,"total_time":0.116425},{"message_size":1024,"total_time":0.07689},{"message_size":1024,"total_time":0.135085},{"message_size":1024,"total_time":0.123404},{"message_size":1024,"total_time":0.122418},{"message_size":1024,"total_time":0.124463}],"throughput":[],"message_size_time":[{"message_size":256,"message_amount":4096,"total_time":127.443919},{"message_size":256,"message_amount":4096,"total_time":113.137021},{"message_size":256,"message_amount":4096,"total_time":112.829812},{"message_size":256,"message_amount":4096,"total_time":119.389388},{"message_size":256,"message_amount":4096,"total_time":113.916727},{"message_size":512,"message_amount":2048,"total_time":58.122774},{"message_size":512,"message_amount":2048,"total_time":57.922145},{"message_size":512,"message_amount":2048,"total_time":66.129929},{"message_size":512,"message_amount":2048,"total_time":63.320403},{"message_size":512,"message_amount":2048,"total_time":62.103317},{"message_size":1024,"message_amount":1024,"total_time":36.647495},{"message_size":1024,"message_amount":1024,"total_time":36.899887},{"message_size":1024,"message_amount":1024,"total_time":38.060665},{"message_size":1024,"message_amount":1024,"total_time":36.824855},{"message_size":1024,"message_amount":1024,"total_time":35.841075}]}
